prune_media/__init__.py
prune_media/apps.py
prune_media/py.typed
prune_media/utils.py
prune_media/management/__init__.py
prune_media/management/commands/__init__.py
prune_media/management/commands/prune_media.py
prune_media/management/commands/show_empty_media_dirs.py
django_prune_media-0.1.7.dist-info/METADATA
django_prune_media-0.1.7.dist-info/WHEEL
django_prune_media-0.1.7.dist-info/licenses/LICENSE
django_prune_media-0.1.7.dist-info/RECORD
