Metadata-Version: 2.4
Name: django-prune-media
Version: 0.1.7
Summary: Adds tools for pruning media files from your django project
Project-URL: Repository, https://codeberg.org/andrlik/django-prune-media
Project-URL: Homepage, https://codeberg.org/andrlik/django-prune-media
Project-URL: Documentation, https://django-prune-media.readthedocs.io/en/latest/
Author-email: Daniel Andrlik <daniel@andrlik.org>
License-Expression: BSD-3-Clause
License-File: LICENSE
Classifier: Development Status :: 4 - Beta
Classifier: Framework :: Django
Classifier: Framework :: Django :: 5.1
Classifier: Framework :: Django :: 5.2
Classifier: License :: OSI Approved :: BSD License
Classifier: Programming Language :: Python :: 3.12
Classifier: Programming Language :: Python :: 3.13
Classifier: Programming Language :: Python :: 3.14
Requires-Python: >=3.12
Requires-Dist: django-typer>=2.3.0
Requires-Dist: django>=5.1.2
